onnxruntime_genai/D3D12Core.dll
onnxruntime_genai/LICENSE
onnxruntime_genai/ThirdPartyNotices.txt
onnxruntime_genai/__init__.py
onnxruntime_genai/_dll_directory.py
onnxruntime_genai/onnxruntime-genai.dll
onnxruntime_genai/onnxruntime_genai.cp310-win_amd64.pyd
onnxruntime_genai/ryzen_mm.dll
onnxruntime_genai/models/builder.py
onnxruntime_genai/models/gguf_model.py
onnxruntime_genai/models/quantized_model.py
onnxruntime_genai_directml_ryzenai-0.7.0.1.dist-info/licenses/LICENSE.txt
onnxruntime_genai_directml_ryzenai-0.7.0.1.dist-info/METADATA
onnxruntime_genai_directml_ryzenai-0.7.0.1.dist-info/WHEEL
onnxruntime_genai_directml_ryzenai-0.7.0.1.dist-info/top_level.txt
onnxruntime_genai_directml_ryzenai-0.7.0.1.dist-info/RECORD
