Metadata-Version: 2.4
Name: onnxruntime-genai-directml-ryzenai
Version: 0.7.0.1
Summary: ONNX Runtime GenAI
Author: Advanced Micro Devices, Inc.
Author-email: Advanced Micro Devices, Inc. <help@amd.com>
License: MIT License
Requires-Dist: numpy>=1.21.6
Requires-Dist: onnxruntime-vitisai==1.22.0.dev20250602
Requires-Dist: voe==1.5.0.dev20250602211920+g3c737cea1
Requires-Dist: model-generate==1.5.0
Dynamic: author
Dynamic: author-email
Dynamic: description
Dynamic: description-content-type
Dynamic: license
Dynamic: requires-dist
Dynamic: summary
License-File: LICENSE.txt
